{
  "model_version": "v2.0_hybrid",
  "weighting": {
    "c2db_boost": 6.0,
    "class_weight_factor": 0.35
  },
  "threshold": 0.5,
  "metrics": {
    "accuracy": 0.9600141668142377,
    "roc_auc": 0.9862601359852163,
    "precision": 0.7557840616966581,
    "recall": 0.9061643835616439,
    "f1_score": 0.8241706899236879,
    "confusion_matrix": {
      "tn": 24460,
      "fp": 855,
      "fn": 274,
      "tp": 2646
    }
  },
  "class_distribution": {
    "non_magnetic": 126570,
    "magnetic": 14601
  },
  "n_features": 64,
  "feature_names": [
    "elem_K",
    "elem_Mn",
    "elem_As",
    "elem_S",
    "elem_F",
    "natoms",
    "elem_P",
    "elem_O",
    "elem_Li",
    "elem_Cl",
    "elem_H",
    "elem_Pd",
    "elem_Se",
    "elem_Te",
    "elem_W",
    "elem_Ge",
    "elem_Zr",
    "elem_Cr",
    "elem_Zn",
    "elem_Hf",
    "elem_Ti",
    "elem_Br",
    "elem_C",
    "elem_Na",
    "elem_Cs",
    "elem_N",
    "elem_Cu",
    "elem_Sn",
    "elem_I",
    "elem_Ag",
    "elem_Sb",
    "elem_Ca",
    "elem_Sc",
    "elem_Ga",
    "elem_Ni",
    "elem_Ir",
    "elem_Rb",
    "elem_B",
    "elem_Ta",
    "elem_Au",
    "elem_V",
    "elem_Nb",
    "elem_Sr",
    "elem_Mo",
    "elem_Y",
    "elem_Fe",
    "elem_Bi",
    "elem_Co",
    "elem_Al",
    "elem_In",
    "elem_Ru",
    "elem_Pb",
    "elem_Tl",
    "elem_Cd",
    "elem_Rh",
    "elem_Os",
    "elem_Hg",
    "elem_Si",
    "elem_Mg",
    "elem_Pt",
    "elem_Re",
    "elem_Be",
    "elem_Ba",
    "elem_Xe"
  ]
}